agentchain/__init__.py
agentchain-0.0.1.dist-info/METADATA
agentchain-0.0.1.dist-info/WHEEL
agentchain-0.0.1.dist-info/RECORD
