Metadata-Version: 2.3
Name: agentchain
Version: 0.0.1
Summary: like langchain but not awful
Project-URL: Homepage, https://github.com/lostmygithubaccount/agentchain
Project-URL: Bug Tracker, https://github.com/lostmygithubaccount/agentchain
Author-email: Cody <cody@dkdc.dev>
Classifier: License :: OSI Approved :: MIT License
Classifier: Operating System :: OS Independent
Classifier: Programming Language :: Python :: 3
Requires-Python: >=3.12
Requires-Dist: stringflow
